bubble_data_api_client/__init__.py
bubble_data_api_client/config.py
bubble_data_api_client/constraints.py
bubble_data_api_client/exceptions.py
bubble_data_api_client/http_client.py
bubble_data_api_client/pool.py
bubble_data_api_client/py.typed
bubble_data_api_client/settings.py
bubble_data_api_client/transport.py
bubble_data_api_client/types.py
bubble_data_api_client/validation.py
bubble_data_api_client/client/__init__.py
bubble_data_api_client/client/client.py
bubble_data_api_client/client/orm.py
bubble_data_api_client/client/raw_client.py
bubble_data_api_client-0.5.3.dist-info/licenses/LICENSE
tests/__init__.py
tests/conftest.py
tests/integration/__init__.py
tests/integration/conftest.py
tests/integration/test_orm.py
tests/integration/test_raw_client.py
tests/unit/__init__.py
tests/unit/test_config.py
tests/unit/test_constraints.py
tests/unit/test_pool.py
tests/unit/test_transport.py
tests/unit/test_types.py
tests/unit/test_validation.py
tests/unit/client/test_create_or_update.py
tests/unit/client/test_orm.py
tests/unit/client/test_raw_client.py
bubble_data_api_client-0.5.3.dist-info/METADATA
bubble_data_api_client-0.5.3.dist-info/WHEEL
bubble_data_api_client-0.5.3.dist-info/top_level.txt
bubble_data_api_client-0.5.3.dist-info/RECORD
