Metadata-Version: 2.4
Name: bubble-data-api-client
Version: 0.5.3
Summary: Async Python client for Bubble Data API with Pydantic ORM, type safety, connection pooling, and configurable retries
License-Expression: MIT
Project-URL: Homepage, https://github.com/bubble-python/bubble-data-api-client
Project-URL: Repository, https://github.com/bubble-python/bubble-data-api-client
Keywords: bubble,bubble.io,async,pydantic,orm,api
Classifier: Programming Language :: Python :: 3.14
Classifier: Programming Language :: Python :: 3.13
Classifier: Programming Language :: Python :: 3.12
Classifier: Typing :: Typed
Requires-Python: >=3.12
License-File: LICENSE
Requires-Dist: httpx[http2]~=0.28
Requires-Dist: pydantic~=2.12
Requires-Dist: tenacity~=9.1
Requires-Dist: typing_extensions>=4.10
Dynamic: license-file
